{
  "disclaimer": "Usage subject to terms: https://openexchangerates.org/terms",
  "license": "https://openexchangerates.org/license",
  "timestamp": 1783008000,
  "base": "USD",
  "rates": {
    "AED": 3.67305,
    "AFN": 63.249998,
    "ALL": 82.455627,
    "AMD": 368.2,
    "ANG": 1.79,
    "AOA": 912.05,
    "ARS": 1491.2475,
    "AUD": 1.442931,
    "AWG": 1.8,
    "AZN": 1.7,
    "BAM": 1.713795,
    "BBD": 2,
    "BDT": 123.279819,
    "BGN": 1.708794,
    "BHD": 0.376965,
    "BIF": 2975.98693,
    "BMD": 1,
    "BND": 1.293534,
    "BOB": 6.924169,
    "BRL": 5.2181,
    "BSD": 1,
    "BTC": 0.000016256036,
    "BTN": 95.385341,
    "BWP": 13.559174,
    "BYN": 2.900668,
    "BZD": 2.010927,
    "CAD": 1.418377,
    "CDF": 2296.393916,
    "CHF": 0.802226,
    "CLF": 0.023458,
    "CLP": 923.24,
    "CNH": 6.785941,
    "CNY": 6.7931,
    "COP": 3371.89,
    "CRC": 455.041439,
    "CUC": 1,
    "CUP": 25.75,
    "CVE": 96.621144,
    "CZK": 21.12625,
    "DJF": 178.047054,
    "DKK": 6.52952,
    "DOP": 59.453923,
    "DZD": 133.326053,
    "EGP": 49.0833,
    "ERN": 15,
    "ETB": 161.379497,
    "EUR": 0.873551,
    "FJD": 2.26665,
    "FKP": 0.748393,
    "GBP": 0.748393,
    "GEL": 2.64,
    "GGP": 0.748393,
    "GHS": 11.335194,
    "GIP": 0.748393,
    "GMD": 73.500003,
    "GNF": 8768.527859,
    "GTQ": 7.627769,
    "GYD": 209.145474,
    "HKD": 7.84256,
    "HNL": 26.760835,
    "HRK": 6.582843,
    "HTG": 130.781123,
    "HUF": 309.1665,
    "IDR": 17985.306919,
    "ILS": 2.99385,
    "IMP": 0.748393,
    "INR": 95.233842,
    "IQD": 1309.824345,
    "IRR": 1376000,
    "ISK": 125.83,
    "JEP": 0.748393,
    "JMD": 157.314114,
    "JOD": 0.709,
    "JPY": 160.9091,
    "KES": 129.31,
    "KGS": 87.45,
    "KHR": 4014.12608,
    "KMF": 433.000105,
    "KPW": 900,
    "KRW": 1538.650777,
    "KWD": 0.309238,
    "KYD": 0.833231,
    "KZT": 479.437741,
    "LAK": 22426.524328,
    "LBP": 89550.648635,
    "LKR": 335.594243,
    "LRD": 181.47246,
    "LSL": 16.36785,
    "LYD": 6.422131,
    "MAD": 9.367997,
    "MDL": 17.608826,
    "MGA": 4247.243487,
    "MKD": 54.072664,
    "MMK": 2099.81,
    "MNT": 3569.47,
    "MOP": 8.077759,
    "MRU": 39.913251,
    "MUR": 47.269999,
    "MVR": 15.45,
    "MWK": 1733.849691,
    "MXN": 17.458139,
    "MYR": 4.0803,
    "MZN": 63.899993,
    "NAD": 16.367922,
    "NGN": 1371.82,
    "NIO": 36.793796,
    "NOK": 9.833773,
    "NPR": 152.590723,
    "NZD": 1.752661,
    "OMR": 0.384501,
    "PAB": 1,
    "PEN": 3.417556,
    "PGK": 4.392659,
    "PHP": 61.446005,
    "PKR": 278.028106,
    "PLN": 3.743766,
    "PYG": 6076.002706,
    "QAR": 3.644728,
    "RON": 4.5708,
    "RSD": 102.530508,
    "RUB": 77.499031,
    "RWF": 1465.801077,
    "SAR": 3.767201,
    "SBD": 8.049104,
    "SCR": 13.514765,
    "SDG": 600.5,
    "SEK": 9.65788,
    "SGD": 1.290984,
    "SHP": 0.748393,
    "SLE": 24.375,
    "SLL": 20969.5,
    "SOS": 571.406649,
    "SRD": 37.5045,
    "SSP": 130.26,
    "STD": 22281.8,
    "STN": 21.468347,
    "SVC": 8.748609,
    "SYP": 13002,
    "SZL": 16.366624,
    "THB": 33.16,
    "TJS": 9.248564,
    "TMT": 3.5,
    "TND": 2.958001,
    "TOP": 2.40776,
    "TRY": 46.6949,
    "TTD": 6.783122,
    "TWD": 31.877301,
    "TZS": 2625.003,
    "UAH": 44.806341,
    "UGX": 3664.50904,
    "USD": 1,
    "UYU": 40.231517,
    "UZS": 11945.18363,
    "VES": 632.572384,
    "VND": 26291.574005,
    "VUV": 119.389,
    "WST": 2.74422,
    "XAF": 573.012071,
    "XAG": 0.01636499,
    "XAU": 0.0002422,
    "XCD": 2.70255,
    "XCG": 1.801915,
    "XDR": 0.715018,
    "XOF": 573.012071,
    "XPD": 0.00078617,
    "XPF": 104.242395,
    "XPT": 0.00061659,
    "YER": 238.599967,
    "ZAR": 16.2336,
    "ZMW": 18.214748,
    "ZWG": 25.3626,
    "ZWL": 322
  }
}