{
  "disclaimer": "Usage subject to terms: https://openexchangerates.org/terms",
  "license": "https://openexchangerates.org/license",
  "timestamp": 1782309600,
  "base": "USD",
  "rates": {
    "AED": 3.6725,
    "AFN": 64.49999,
    "ALL": 83.283734,
    "AMD": 367.93,
    "ANG": 1.79,
    "AOA": 912.6001,
    "ARS": 1475.9873,
    "AUD": 1.449448,
    "AWG": 1.80125,
    "AZN": 1.7,
    "BAM": 1.724577,
    "BBD": 2,
    "BDT": 122.992818,
    "BGN": 1.724416,
    "BHD": 0.377147,
    "BIF": 2984.824262,
    "BMD": 1,
    "BND": 1.298984,
    "BOB": 6.909809,
    "BRL": 5.2164,
    "BSD": 1,
    "BTC": 0.000016345125,
    "BTN": 94.624106,
    "BWP": 13.624818,
    "BYN": 2.818068,
    "BZD": 2.01104,
    "CAD": 1.422982,
    "CDF": 2299.061848,
    "CHF": 0.8126,
    "CLF": 0.023357,
    "CLP": 919.25,
    "CNH": 6.816892,
    "CNY": 6.7913,
    "COP": 3446.33,
    "CRC": 455.187023,
    "CUC": 1,
    "CUP": 25.75,
    "CVE": 97.222568,
    "CZK": 21.375173,
    "DJF": 178.061648,
    "DKK": 6.589864,
    "DOP": 58.613455,
    "DZD": 133.561684,
    "EGP": 49.5871,
    "ERN": 15,
    "ETB": 161.211804,
    "EUR": 0.881503,
    "FJD": 2.24875,
    "FKP": 0.759772,
    "GBP": 0.759772,
    "GEL": 2.645,
    "GGP": 0.759772,
    "GHS": 11.199781,
    "GIP": 0.759772,
    "GMD": 72.50001,
    "GNF": 8761.512761,
    "GTQ": 7.627361,
    "GYD": 209.162736,
    "HKD": 7.839838,
    "HNL": 26.755727,
    "HRK": 6.643037,
    "HTG": 130.744964,
    "HUF": 313.860315,
    "IDR": 17980.88211,
    "ILS": 2.98356,
    "IMP": 0.759772,
    "INR": 94.369143,
    "IQD": 1309.874966,
    "IRR": 1375000,
    "ISK": 126.77,
    "JEP": 0.759772,
    "JMD": 157.488637,
    "JOD": 0.709,
    "JPY": 161.75263636,
    "KES": 129.51,
    "KGS": 87.45,
    "KHR": 4017.464753,
    "KMF": 431.000289,
    "KPW": 900,
    "KRW": 1544.47657,
    "KWD": 0.309381,
    "KYD": 0.833297,
    "KZT": 486.622483,
    "LAK": 22187.873403,
    "LBP": 89560.818385,
    "LKR": 335.228906,
    "LRD": 182.134825,
    "LSL": 16.623945,
    "LYD": 6.430933,
    "MAD": 9.401479,
    "MDL": 17.590241,
    "MGA": 4177.119606,
    "MKD": 54.351135,
    "MMK": 2099.81,
    "MNT": 3569.47,
    "MOP": 8.076099,
    "MRU": 39.982188,
    "MUR": 48.210003,
    "MVR": 15.46,
    "MWK": 1733.878759,
    "MXN": 17.636484,
    "MYR": 4.138,
    "MZN": 63.899993,
    "NAD": 16.623945,
    "NGN": 1373.28,
    "NIO": 36.797319,
    "NOK": 9.856558,
    "NPR": 151.394766,
    "NZD": 1.771156,
    "OMR": 0.384497,
    "PAB": 1,
    "PEN": 3.391297,
    "PGK": 4.386951,
    "PHP": 61.043,
    "PKR": 278.100488,
    "PLN": 3.779872,
    "PYG": 6099.345831,
    "QAR": 3.635217,
    "RON": 4.6158,
    "RSD": 103.432626,
    "RUB": 74.89574,
    "RWF": 1468.893796,
    "SAR": 3.754889,
    "SBD": 8.065041,
    "SCR": 13.653598,
    "SDG": 600.5,
    "SEK": 9.767257,
    "SGD": 1.298127,
    "SHP": 0.759772,
    "SLE": 24.75,
    "SLL": 20969.5,
    "SOS": 571.478392,
    "SRD": 37.483,
    "SSP": 130.26,
    "STD": 22281.8,
    "STN": 21.603509,
    "SVC": 8.749173,
    "SYP": 13002,
    "SZL": 16.517116,
    "THB": 33.404,
    "TJS": 9.284423,
    "TMT": 3.51,
    "TND": 2.972467,
    "TOP": 2.40776,
    "TRY": 46.49729,
    "TTD": 6.780184,
    "TWD": 31.747499,
    "TZS": 2620.503,
    "UAH": 44.884552,
    "UGX": 3689.328406,
    "USD": 1,
    "UYU": 40.118518,
    "UZS": 12024.238814,
    "VES": 616.864713,
    "VND": 26333.114347,
    "VUV": 119.389,
    "WST": 2.74422,
    "XAF": 578.227993,
    "XAG": 0.01680002,
    "XAU": 0.00024762,
    "XCD": 2.70255,
    "XCG": 1.802141,
    "XDR": 0.716966,
    "XOF": 578.227993,
    "XPD": 0.00083364,
    "XPF": 105.191276,
    "XPT": 0.00061797,
    "YER": 238.649953,
    "ZAR": 16.588228,
    "ZMW": 18.024056,
    "ZWG": 25.3626,
    "ZWL": 322
  }
}